dishhq/__init__.py
dishhq/dish.py
dishhq-0.1.1.dist-info/LICENSE
dishhq-0.1.1.dist-info/METADATA
dishhq-0.1.1.dist-info/WHEEL
dishhq-0.1.1.dist-info/top_level.txt
dishhq-0.1.1.dist-info/RECORD
